LICENSE-3RD-PARTY.txt
LICENSE.txt
MANIFEST.in
README.rst
setup.py
lemoncheesecake/__init__.py
lemoncheesecake/api.py
lemoncheesecake/events.py
lemoncheesecake/exceptions.py
lemoncheesecake/filter.py
lemoncheesecake/fixture.py
lemoncheesecake/metadatapolicy.py
lemoncheesecake/project.py
lemoncheesecake/runner.py
lemoncheesecake/session.py
lemoncheesecake/task.py
lemoncheesecake/testtree.py
lemoncheesecake.egg-info/PKG-INFO
lemoncheesecake.egg-info/SOURCES.txt
lemoncheesecake.egg-info/dependency_links.txt
lemoncheesecake.egg-info/entry_points.txt
lemoncheesecake.egg-info/requires.txt
lemoncheesecake.egg-info/top_level.txt
lemoncheesecake/bdd/__init__.py
lemoncheesecake/bdd/behave.py
lemoncheesecake/cli/__init__.py
lemoncheesecake/cli/command.py
lemoncheesecake/cli/main.py
lemoncheesecake/cli/utils.py
lemoncheesecake/cli/commands/__init__.py
lemoncheesecake/cli/commands/bootstrap.py
lemoncheesecake/cli/commands/check.py
lemoncheesecake/cli/commands/diff.py
lemoncheesecake/cli/commands/fixtures.py
lemoncheesecake/cli/commands/report.py
lemoncheesecake/cli/commands/run.py
lemoncheesecake/cli/commands/show.py
lemoncheesecake/cli/commands/stats.py
lemoncheesecake/cli/commands/top.py
lemoncheesecake/cli/commands/version.py
lemoncheesecake/helpers/__init__.py
lemoncheesecake/helpers/console.py
lemoncheesecake/helpers/introspection.py
lemoncheesecake/helpers/moduleimport.py
lemoncheesecake/helpers/orderedset.py
lemoncheesecake/helpers/resources.py
lemoncheesecake/helpers/terminalsize.py
lemoncheesecake/helpers/text.py
lemoncheesecake/helpers/threading.py
lemoncheesecake/helpers/time.py
lemoncheesecake/helpers/typecheck.py
lemoncheesecake/matching/__init__.py
lemoncheesecake/matching/matcher.py
lemoncheesecake/matching/operations.py
lemoncheesecake/matching/matchers/__init__.py
lemoncheesecake/matching/matchers/composites.py
lemoncheesecake/matching/matchers/dict_.py
lemoncheesecake/matching/matchers/list_.py
lemoncheesecake/matching/matchers/string.py
lemoncheesecake/matching/matchers/types_.py
lemoncheesecake/matching/matchers/value.py
lemoncheesecake/reporting/__init__.py
lemoncheesecake/reporting/backend.py
lemoncheesecake/reporting/console.py
lemoncheesecake/reporting/loader.py
