Metadata-Version: 2.1
Name: lemoncheesecake
Version: 1.15.0
Summary: Test Storytelling
Home-page: http://lemoncheesecake.io
Author: Nicolas Delon
Author-email: nicolas.delon@gmail.com
License: Apache License (Version 2.0)
Project-URL: Documentation, http://docs.lemoncheesecake.io/
Project-URL: Source, https://github.com/lemoncheesecake/lemoncheesecake
Project-URL: Tracker, https://github.com/lemoncheesecake/lemoncheesecake/issues
Keywords: QA tests functional
Platform: UNKNOWN
Classifier: Development Status :: 5 - Production/Stable
Classifier: Environment :: Console
Classifier: Intended Audience :: Developers
Classifier: License :: OSI Approved :: Apache Software License
Classifier: Operating System :: MacOS
Classifier: Operating System :: Microsoft :: Windows
Classifier: Operating System :: POSIX
Classifier: Programming Language :: Python :: 3
Classifier: Programming Language :: Python :: 3.8
Classifier: Programming Language :: Python :: 3.9
Classifier: Programming Language :: Python :: 3.10
Classifier: Programming Language :: Python :: 3.11
Classifier: Programming Language :: Python :: 3.12
Classifier: Programming Language :: Python :: 3 :: Only
Classifier: Topic :: Software Development :: Quality Assurance
Classifier: Topic :: Software Development :: Testing
Requires-Python: >=3.8
Provides-Extra: reportportal
Provides-Extra: slack
License-File: LICENSE-3RD-PARTY.txt
License-File: LICENSE.txt
